<annotation>
	<folder>XML</folder>
	<filename>dji-0381crop_0_2.png</filename>
	<path>/content/plantas/conj_ima_new/train/dji-0381crop_0_2.png</path>
	<source>
		<database>Unknown</database>
	</source>
	<size>
		<width>512</width>
		<height>512</height>
		<depth>3</depth>
	</size>
	<segmented>0</segmented>
	<object>
		<name>planta</name>
		<pose>Unspecified</pose>
		<truncated>0</truncated>
		<difficult>0</difficult>
		<bndbox>
			<xmin>56</xmin>
			<ymin>211</ymin>
			<xmax>136</xmax>
			<ymax>304</ymax>
		</bndbox>
	</object>
	<object>
		<name>planta</name>
		<pose>Unspecified</pose>
		<truncated>0</truncated>
		<difficult>0</difficult>
		<bndbox>
			<xmin>363</xmin>
			<ymin>23</ymin>
			<xmax>416</xmax>
			<ymax>92</ymax>
		</bndbox>
	</object>
	<object>
		<name>planta</name>
		<pose>Unspecified</pose>
		<truncated>0</truncated>
		<difficult>0</difficult>
		<bndbox>
			<xmin>119</xmin>
			<ymin>221</ymin>
			<xmax>189</xmax>
			<ymax>314</ymax>
		</bndbox>
	</object>
	<object>
		<name>planta</name>
		<pose>Unspecified</pose>
		<truncated>0</truncated>
		<difficult>0</difficult>
		<bndbox>
			<xmin>236</xmin>
			<ymin>55</ymin>
			<xmax>336</xmax>
			<ymax>106</ymax>
		</bndbox>
	</object>
	<object>
		<name>planta</name>
		<pose>Unspecified</pose>
		<truncated>0</truncated>
		<difficult>0</difficult>
		<bndbox>
			<xmin>158</xmin>
			<ymin>25</ymin>
			<xmax>217</xmax>
			<ymax>123</ymax>
		</bndbox>
	</object>
	<object>
		<name>planta</name>
		<pose>Unspecified</pose>
		<truncated>0</truncated>
		<difficult>0</difficult>
		<bndbox>
			<xmin>41</xmin>
			<ymin>10</ymin>
			<xmax>92</xmax>
			<ymax>127</ymax>
		</bndbox>
	</object>
	<object>
		<name>planta</name>
		<pose>Unspecified</pose>
		<truncated>0</truncated>
		<difficult>0</difficult>
		<bndbox>
			<xmin>232</xmin>
			<ymin>225</ymin>
			<xmax>284</xmax>
			<ymax>307</ymax>
		</bndbox>
	</object>
	<object>
		<name>planta</name>
		<pose>Unspecified</pose>
		<truncated>0</truncated>
		<difficult>0</difficult>
		<bndbox>
			<xmin>270</xmin>
			<ymin>433</ymin>
			<xmax>372</xmax>
			<ymax>496</ymax>
		</bndbox>
	</object>
	<object>
		<name>planta</name>
		<pose>Unspecified</pose>
		<truncated>0</truncated>
		<difficult>0</difficult>
		<bndbox>
			<xmin>141</xmin>
			<ymin>426</ymin>
			<xmax>221</xmax>
			<ymax>498</ymax>
		</bndbox>
	</object>
	<object>
		<name>planta</name>
		<pose>Unspecified</pose>
		<truncated>0</truncated>
		<difficult>0</difficult>
		<bndbox>
			<xmin>387</xmin>
			<ymin>429</ymin>
			<xmax>465</xmax>
			<ymax>509</ymax>
		</bndbox>
	</object>
</annotation>
